pds_one/__init__.py
pds_one/functions.py
pds_one/main.py
pds_one/settings.py
pds_one/tests/__init__.py
pds_one/tests/server_tests.py
pds_one-1.6.2.dist-info/METADATA
pds_one-1.6.2.dist-info/WHEEL
pds_one-1.6.2.dist-info/top_level.txt
pds_one-1.6.2.dist-info/RECORD
