Metadata-Version: 2.1
Name: pds-one
Version: 1.6.2
Author: PunchyArchy
Author-email: ksmdrmvscthny@gmail.com
Requires-Dist: pyserial ==3.5
